{
  "title": "before we drink hard again.",
  "date": "2007-04-27",
  "format": "cd",
  "notes": "for jordan s",
  "artOfTheMixUrl": "https://www.artofthemix.org/mix/111803",
  "tracks": [
    {
      "title": "absinthe party at the fly honey warehouse",
      "artist": "minus the bear"
    },
    {
      "title": "cold beer and cigarettes (acoustic)",
      "artist": "david bazan"
    },
    {
      "title": "love is like a bottle of gin",
      "artist": "magnetic fields"
    },
    {
      "title": "champagne from a paper cup",
      "artist": "death cab for cutie"
    },
    {
      "title": "he brings out the whiskey in me",
      "artist": "amy millan"
    },
    {
      "title": "killian's red",
      "artist": "nada surf"
    },
    {
      "title": "whiskey lipped kisser",
      "artist": "love of everything"
    },
    {
      "title": "virtue and wine",
      "artist": "sondre lerche"
    },
    {
      "title": "long distance drunk",
      "artist": "modest mouse"
    },
    {
      "title": "whiskey",
      "artist": "voxtrot"
    },
    {
      "title": "gin and platonic",
      "artist": "joan of arc"
    },
    {
      "title": "stoli on the rocks",
      "artist": "ghosts and vodka"
    },
    {
      "title": "soco amaretto lime",
      "artist": "brand new"
    }
  ]
}
