{
  "title": "carelessly growing up and growing old.",
  "date": "2007-01-10",
  "format": "cd",
  "notes": "",
  "artOfTheMixUrl": "https://www.artofthemix.org/mix/109498",
  "tracks": [
    {
      "title": "brace your face",
      "artist": "aloha"
    },
    {
      "title": "our swords",
      "artist": "band of horses"
    },
    {
      "title": "lullaby",
      "artist": "gravity and henry"
    },
    {
      "title": "starlight",
      "artist": "muse"
    },
    {
      "title": "concrete bed",
      "artist": "nada surf"
    },
    {
      "title": "parade of the punk rock t-shirts",
      "artist": "maritime"
    },
    {
      "title": "natural disaster",
      "artist": "headphones"
    },
    {
      "title": "the chills",
      "artist": "peter bjorn and john"
    },
    {
      "title": "special",
      "artist": "mew"
    },
    {
      "title": "sunny days",
      "artist": "jars of clay"
    },
    {
      "title": "wolf like me",
      "artist": "tv on the radio"
    },
    {
      "title": "munich",
      "artist": "editors"
    },
    {
      "title": "we intertwined",
      "artist": "hush sound"
    },
    {
      "title": "the secret",
      "artist": "brandtson"
    },
    {
      "title": "grass",
      "artist": "animal collective"
    }
  ]
}
