{
  "title": "italy (it goes on).",
  "date": "2007-05-24",
  "format": "cassette",
  "notes": "for aeriel",
  "artOfTheMixUrl": "https://www.artofthemix.org/mix/112399",
  "tracks": [
    {
      "title": "postcards from italy",
      "artist": "beirut"
    },
    {
      "title": "pachuca sunrise",
      "artist": "minus the bear"
    },
    {
      "title": "napoleon says",
      "artist": "phoenix"
    },
    {
      "title": "happiness (the gondola man)",
      "artist": "elliott smith"
    },
    {
      "title": "italian wardrobe",
      "artist": "broken spindles"
    },
    {
      "title": "sicily",
      "artist": "youth group"
    },
    {
      "title": "italian leather sofa",
      "artist": "cake"
    },
    {
      "title": "greyhound",
      "artist": "john vanderslice"
    },
    {
      "title": "score from augusta",
      "artist": "beulah"
    },
    {
      "title": "italy",
      "artist": "akron/family"
    },
    {
      "title": "vittorio e",
      "artist": "spoon"
    },
    {
      "title": "byzantine",
      "artist": "pinback"
    },
    {
      "title": "mflan=",
      "artist": "sigur r=s"
    }
  ],
  "sideA": [
    {
      "title": "postcards from italy",
      "artist": "beirut"
    },
    {
      "title": "pachuca sunrise",
      "artist": "minus the bear"
    },
    {
      "title": "napoleon says",
      "artist": "phoenix"
    },
    {
      "title": "happiness (the gondola man)",
      "artist": "elliott smith"
    },
    {
      "title": "italian wardrobe",
      "artist": "broken spindles"
    },
    {
      "title": "sicily",
      "artist": "youth group"
    },
    {
      "title": "italian leather sofa",
      "artist": "cake"
    }
  ],
  "sideB": [
    {
      "title": "greyhound",
      "artist": "john vanderslice"
    },
    {
      "title": "score from augusta",
      "artist": "beulah"
    },
    {
      "title": "italy",
      "artist": "akron/family"
    },
    {
      "title": "vittorio e",
      "artist": "spoon"
    },
    {
      "title": "byzantine",
      "artist": "pinback"
    },
    {
      "title": "mflan=",
      "artist": "sigur r=s"
    }
  ]
}
