{
  "title": "sitting on the shoreline.",
  "date": "2007-05-03",
  "format": "cassette",
  "notes": "for sara t",
  "artOfTheMixUrl": "https://www.artofthemix.org/mix/111950",
  "tracks": [
    {
      "title": "beach party tonight",
      "artist": "yo la tengo"
    },
    {
      "title": "collide the tide",
      "artist": "chin up chin up"
    },
    {
      "title": "tripoli (starfish pool remix)",
      "artist": "pinback"
    },
    {
      "title": "ocean breathes salty",
      "artist": "modest mouse"
    },
    {
      "title": "barrier reef",
      "artist": "old 97's"
    },
    {
      "title": "beachcomber blues",
      "artist": "dolorean"
    },
    {
      "title": "seaweed",
      "artist": "fruit bats"
    },
    {
      "title": "ocean floored rmx",
      "artist": "her space holiday"
    },
    {
      "title": "clothes of sand",
      "artist": "calexico"
    },
    {
      "title": "palm trees in the fecking bahamas",
      "artist": "don caballero"
    },
    {
      "title": "coastal",
      "artist": "benton falls"
    },
    {
      "title": "tide changes",
      "artist": "hush sound"
    },
    {
      "title": "above the waves",
      "artist": "jealous sound"
    },
    {
      "title": "the rising tide",
      "artist": "sunny day real estate"
    },
    {
      "title": "cripple and the starfish",
      "artist": "antony and the johnstons"
    },
    {
      "title": "ease your feet in the sea",
      "artist": "belle and sebastian"
    },
    {
      "title": "swallowed in the sea",
      "artist": "coldplay"
    },
    {
      "title": "crest",
      "artist": "tortoise"
    },
    {
      "title": "seashell tale",
      "artist": "bright eyes"
    },
    {
      "title": "clam, crab, cockle, cowrie",
      "artist": "joanna newsom"
    },
    {
      "title": "tropicana",
      "artist": "ratatat"
    },
    {
      "title": "the ocean",
      "artist": "mae"
    }
  ],
  "sideA": [
    {
      "title": "beach party tonight",
      "artist": "yo la tengo"
    },
    {
      "title": "collide the tide",
      "artist": "chin up chin up"
    },
    {
      "title": "tripoli (starfish pool remix)",
      "artist": "pinback"
    },
    {
      "title": "ocean breathes salty",
      "artist": "modest mouse"
    },
    {
      "title": "barrier reef",
      "artist": "old 97's"
    },
    {
      "title": "beachcomber blues",
      "artist": "dolorean"
    },
    {
      "title": "seaweed",
      "artist": "fruit bats"
    },
    {
      "title": "ocean floored rmx",
      "artist": "her space holiday"
    },
    {
      "title": "clothes of sand",
      "artist": "calexico"
    },
    {
      "title": "palm trees in the fecking bahamas",
      "artist": "don caballero"
    },
    {
      "title": "coastal",
      "artist": "benton falls"
    }
  ],
  "sideB": [
    {
      "title": "tide changes",
      "artist": "hush sound"
    },
    {
      "title": "above the waves",
      "artist": "jealous sound"
    },
    {
      "title": "the rising tide",
      "artist": "sunny day real estate"
    },
    {
      "title": "cripple and the starfish",
      "artist": "antony and the johnstons"
    },
    {
      "title": "ease your feet in the sea",
      "artist": "belle and sebastian"
    },
    {
      "title": "swallowed in the sea",
      "artist": "coldplay"
    },
    {
      "title": "crest",
      "artist": "tortoise"
    },
    {
      "title": "seashell tale",
      "artist": "bright eyes"
    },
    {
      "title": "clam, crab, cockle, cowrie",
      "artist": "joanna newsom"
    },
    {
      "title": "tropicana",
      "artist": "ratatat"
    },
    {
      "title": "the ocean",
      "artist": "mae"
    }
  ]
}
