{
  "title": "the heart is a risky fuel to burn.",
  "date": "2007-11-27",
  "format": "cd",
  "notes": "for stephen",
  "artOfTheMixUrl": "https://www.artofthemix.org/mix/116168",
  "tracks": [
    {
      "title": "oh, it is love",
      "artist": "hellogoodbye"
    },
    {
      "title": "stephen",
      "artist": "voxtrot"
    },
    {
      "title": "before you were born",
      "artist": "rocky votolato"
    },
    {
      "title": "your rocky spine",
      "artist": "great lake swimmers"
    },
    {
      "title": "if we should fall",
      "artist": "cub country"
    },
    {
      "title": "how we breathe",
      "artist": "pinback"
    },
    {
      "title": "lay down your arms",
      "artist": "flowers from the man who shot your cousin"
    },
    {
      "title": "being in love",
      "artist": "songs: ohia"
    },
    {
      "title": "one and one makes two",
      "artist": "johnny cash"
    },
    {
      "title": "november starlings",
      "artist": "trembling blue stars"
    },
    {
      "title": "come lie down with me (and sing my song)",
      "artist": "elf power"
    },
    {
      "title": "apart",
      "artist": "damien jurado"
    },
    {
      "title": "if all my days go by",
      "artist": "maritime"
    },
    {
      "title": "promise what you will",
      "artist": "iron and wine"
    },
    {
      "title": "the cold, the dark & the silence",
      "artist": "sea wolf"
    },
    {
      "title": "love love love",
      "artist": "the mountain goats"
    }
  ]
}
